morf/__init__.py
morf/bindadapters.py
morf/choices.py
morf/compat.py
morf/exceptions.py
morf/fields.py
morf/form.py
morf/formrender.py
morf/htmlbuilder.py
morf/htmlform.py
morf/iterable.py
morf/render.py
morf/types.py
morf/validators.py
morf/widgets.py
morf-2.0.0.dist-info/LICENSE.txt
morf-2.0.0.dist-info/METADATA
morf-2.0.0.dist-info/WHEEL
morf-2.0.0.dist-info/top_level.txt
morf-2.0.0.dist-info/RECORD
