Metadata-Version: 2.1
Name: morf
Version: 2.0.0
Summary: HTML Form Validation and Rendering
Home-page: https://ollycope.com/software/morf/
Author: Oliver Cope
Author-email: oliver@redgecko.org
License: Apache License 2.0
Keywords: form forms validation schema html
Platform: UNKNOWN
Classifier: Development Status :: 5 - Production/Stable
Classifier: Intended Audience :: Developers
Classifier: License :: OSI Approved :: Apache Software License
Classifier: Operating System :: OS Independent
Classifier: Programming Language :: Python :: 3
Classifier: Programming Language :: Python :: 3 :: Only
Classifier: Topic :: Text Processing
Classifier: Topic :: Text Processing :: Markup
License-File: LICENSE.txt
Requires-Dist: python-dateutil
Requires-Dist: markupsafe
Requires-Dist: jinja2
